{
  "project": {
    "name": "닷믹스베스트 v4 (풀 사이클)",
    "fps": 30,
    "width": 1280,
    "height": 720
  },
  "clipDir": "<repo>/media/dotmix_src",
  "intro": null,
  "outro": null,
  "segments": [
    {
      "clip": "IMG_3653.mov",
      "in": 0,
      "out": 3,
      "speed": 1,
      "volume": 1,
      "subtitle": "상자 안 내용물 정적 컷, DOT yarn 라벨이 선명하게 보임, 손 없음"
    },
    {
      "clip": "IMG_3653.mov",
      "in": 10,
      "out": 13,
      "speed": 1,
      "volume": 1,
      "subtitle": "손이 GEEK 라벨 붙은 비닐 포장 뭉치를 상자에서 들어올리는 리빌 순간"
    },
    {
      "clip": "VID_20260211_151549_008.mp4",
      "in": 4,
      "out": 7,
      "speed": 1,
      "volume": 1,
      "subtitle": "열린 지퍼백 안 도트얀 세트 리빌 - 회색 실타래 두 뭉치, 가운데 DOT yarn 라벨 튜브, 검은 원단 조각들이 나란히 보임. 손은 프레임 밖/흐림, 정지 홀드"
    },
    {
      "clip": "VID_20260211_153300_010.mp4",
      "in": 0,
      "out": 3,
      "speed": 1,
      "volume": 1,
      "subtitle": "검정색 실타래를 양손으로 들고 카메라 쪽으로 보여주는 동작, 파란 라벨에 Wool Roving 글자가 보임(얼굴은 턱선 아래 프레이밍이라 입술 미노출)"
    },
    {
      "clip": "VID_20260211_155414_011.mp4",
      "in": 0,
      "out": 60,
      "speed": 14,
      "volume": 1,
      "subtitle": "(빨리감기) 고양이가 옆에서 계속 자는 가운데 인물이 검은 장식끈/코드를 손으로 만지작거리며 매듭짓고 실을 입으로 끊는 동작이 반복됨. 카메라·구도 고정, 인물 이동 없음 - 배속 커넥터 후보(60초 격자로는 세부 변화가 안 보일 만큼 균질함)"
    },
    {
      "clip": "VID_20260211_155414_011.mp4",
      "in": 538,
      "out": 541,
      "speed": 1,
      "volume": 1,
      "subtitle": "고개를 푹 숙여 앞머리가 얼굴을 완전히 가린 채 검은 끈의 매듭/실을 손으로 매만지는 클로즈업, 이목구비는 머리카락에 가려 보이지 않음"
    },
    {
      "clip": "VID_20260211_155414_011.mp4",
      "in": 658,
      "out": 661,
      "speed": 1,
      "volume": 1,
      "subtitle": "머리카락이 얼굴 옆면을 가린 채 고개를 기울여 고양이 쪽으로 다가가는 모습, 카메라에 가까운 고양이가 화면을 채움, 보이는 부분은 턱선까지만이고 입술은 가려짐"
    },
    {
      "clip": "VID_20260211_155414_011.mp4",
      "in": 880,
      "out": 883,
      "speed": 1,
      "volume": 1,
      "subtitle": "인물이 화면 밖으로 나가고 고양이 혼자 소파 위 완성물(원사 뭉치가 담긴 봉투 옆)에 앉아 카메라를 가만히 응시함, 사람 얼굴 노출 전혀 없음"
    },
    {
      "clip": "VID_20260211_155414_011.mp4",
      "in": 916,
      "out": 919,
      "speed": 1,
      "volume": 1,
      "subtitle": "카메라 앞으로 손을 뻗어 'DOT yarn' 라벨이 붙은 원사 제품을 들어 보여주는 리빌샷(엄지척 제스처 동반), 얼굴은 화면 최상단에 이마/헤어라인 정도만 살짝 걸리고 입술은 보이지 않음"
    },
    {
      "clip": "VID_20260211_160940_012.mp4",
      "in": 0,
      "out": 3,
      "speed": 1,
      "volume": 1,
      "subtitle": "손으로 DOT yarn 라벨이 정면으로 보이게 들고 있는 정적인 제품 오브젝트 샷, 얼굴 없음"
    },
    {
      "clip": "VID_20260211_182318_013.mp4",
      "in": 0,
      "out": 45,
      "speed": 14,
      "volume": 1,
      "subtitle": "(빨리감기) 완성된 뜨개천을 들고 각도만 바꿔가며 계속 보여주는 반복 동작, 내용 변화 거의 없음"
    },
    {
      "clip": "VID_20260211_182604_014.mp4",
      "in": 4,
      "out": 6,
      "speed": 1,
      "volume": 1,
      "subtitle": "화면이 손 클로즈업으로 전환된 것으로 보임(정확한 전환 시점은 4~5초 사이로 불확실), 손가락 사이로 분홍빛 실 가닥 같은 것을 당기는 모습, 얼굴 미노출"
    },
    {
      "clip": "VID_20260211_182828_016.mp4",
      "in": 0,
      "out": 60,
      "speed": 14,
      "volume": 1,
      "subtitle": "(빨리감기) 의자에 앉아 니트를 뜨는 동작만 반복되는 롱테이크, 프레임 간 변화 거의 없음. 이 구간의 와이드샷은 얼굴(눈~입)이 계속 노출되어 있어 초안 채택 시 세로 크롭 없이는 사용 불가."
    },
    {
      "clip": "VID_20260211_182828_016.mp4",
      "in": 238,
      "out": 241,
      "speed": 1,
      "volume": 1,
      "subtitle": "완성 중인 니트 조각(검정 바탕 흰 점무늬)을 두 손으로 들어 카메라 쪽으로 보여줌, 얼굴은 프레임 밖(어깨선 위로 잘림)"
    },
    {
      "clip": "VID_20260211_182828_016.mp4",
      "in": 245,
      "out": 248,
      "speed": 1,
      "volume": 1,
      "subtitle": "같은 니트 조각을 더 넓게 펼쳐 무늬가 잘 보이게 보여주는 동작, 팔이 카메라 쪽으로 다가오며 마무리, 얼굴 프레임 밖"
    },
    {
      "clip": "VID_20260211_184457_017.mp4",
      "in": 0,
      "out": 3,
      "speed": 1,
      "volume": 1,
      "subtitle": "나무 테이블 위 투명 케이스에 담긴 빵/케이크 한 조각과 옆에 펼쳐진 GENTZ CAKES 포장 비닐, 정적 오브젝트 샷, 손이나 얼굴 없음"
    },
    {
      "clip": "VID_20260211_185413_018.mp4",
      "in": 0,
      "out": 60,
      "speed": 14,
      "volume": 1,
      "subtitle": "(빨리감기) 소파에 앉아 검정 스팽글사로 뜨개질만 반복. 로우앵글 고정 카메라라 입술이 거의 항상 노출되고(0/60/120/180/240/300/360/420초 교차 확인), 뜨개질감을 입 근처로 들어도 완전히 가리지 못함. 장면 변화 없음 — 배속 커넥터 후보."
    },
    {
      "clip": "VID_20260211_185413_018.mp4",
      "in": 461,
      "out": 462.5,
      "speed": 1,
      "volume": 1,
      "subtitle": "양손으로 검정 스팽글 니트 조각을 팽팽히 당겨 패턴/코 상태를 확인하는 손 클로즈업, 이 짧은 구간에서만 우연히 얼굴이 프레임 밖으로 완전히 가려짐(직전·직후 프레임은 모두 입술 노출로 확인됨). 배경은 주황 서랍장, 조명 양호. 다만 지속시간이 1.5초로 컷 관행(2~4초)보다 짧음 — 전후로 늘리면 바로 얼굴 노출이라 확장 불가."
    },
    {
      "clip": "VID_20260211_185413_018.mp4",
      "in": 490,
      "out": 550,
      "speed": 14,
      "volume": 1,
      "subtitle": "(빨리감기) 기지개(474~486초) 이후 다시 연속 뜨개질. 코가 늘며 조각이 서서히 커지지만(540~900초 구간 비교로 확인) 단일 리빌 시점이 없는 점진적 변화라 컷으로 뽑기 어려움. 1020초 무렵부터 손이 렌즈를 가리기 시작해 1028초에 완전히 가림. 배속 커넥터 후보."
    },
    {
      "clip": "VID_20260211_191139_019.mp4",
      "in": 0,
      "out": 3,
      "speed": 1,
      "volume": 1,
      "subtitle": "짙은 남색 바탕에 흰 스팽클이 박힌 뜨개 조각을 두 손으로 들어 스티치 결을 보여줌, 프레임 상단에 인물 턱선만 살짝 걸림(입술은 보이지 않음), 초점 선명"
    },
    {
      "clip": "VID_20260211_204949_020.mp4",
      "in": 0,
      "out": 39.87,
      "speed": 14,
      "volume": 1,
      "subtitle": "(빨리감기) 동일한 니트 스와치를 손으로 들고 각도만 바꿔가며 반복적으로 보여주는 컷 전환 없는 롱테이크 전체 구간"
    },
    {
      "clip": "VID_20260211_204949_020.mp4",
      "in": 4,
      "out": 7,
      "speed": 1,
      "volume": 1,
      "subtitle": "완성된 회색/검정 스페클 배색 니트 스와치를 두 손으로 펼쳐 보여주는 장면으로 보임, 얼굴 없이 상반신 아래만 보임, 배색 경계선이 선명하게 드러남"
    },
    {
      "clip": "VID_20260211_204949_020.mp4",
      "in": 14,
      "out": 17,
      "speed": 1,
      "volume": 1,
      "subtitle": "니트 스와치 표면 질감을 가까이서 보여주는 손 클로즈업으로 보임, 얼굴 없음"
    },
    {
      "clip": "VID_20260211_204949_020.mp4",
      "in": 19,
      "out": 22,
      "speed": 1,
      "volume": 1,
      "subtitle": "배색 경계 부분을 다시 펼쳐 보여주는 장면, 얼굴 없이 손과 스와치만 보임"
    },
    {
      "clip": "VID_20260211_204949_020.mp4",
      "in": 33,
      "out": 36,
      "speed": 1,
      "volume": 1,
      "subtitle": "손가락으로 실 끝을 만지작거리는 것으로 보이는 클로즈업, 얼굴은 화면 상단 가장자리에 턱선 정도만 살짝 걸리는 것으로 보임(입술은 보이지 않음)"
    },
    {
      "clip": "VID_20260211_220150_021.mp4",
      "in": 10,
      "out": 13,
      "speed": 1,
      "volume": 1,
      "subtitle": "크림색 조임끈 파우치에서 회색+검은 물방울무늬 배색 뜨개 조각을 양손으로 꺼내는 클로즈업, 얼굴 미노출"
    },
    {
      "clip": "VID_20260211_220150_021.mp4",
      "in": 38,
      "out": 41,
      "speed": 1,
      "volume": 1,
      "subtitle": "뜨던 회색 조각을 검은 물방울무늬 조각과 나란히 펼쳐 크기/진행 상황을 비교하는 손동작"
    },
    {
      "clip": "VID_20260211_220150_021.mp4",
      "in": 41,
      "out": 101,
      "speed": 14,
      "volume": 1,
      "subtitle": "(빨리감기) 고정 앵글에서 반복적인 뜨개질 동작만 지속, 파츠 구성(회색 몸판+검은 물방울무늬)이나 자세 변화 없음 - 14배속 커넥터 후보 대구간(약 400초)"
    },
    {
      "clip": "VID_20260211_220150_021.mp4",
      "in": 149,
      "out": 152,
      "speed": 1,
      "volume": 1,
      "subtitle": "회색 실로 대바늘을 움직이며 뜨는 손 클로즈업, 반복 구간의 대표 컷"
    },
    {
      "clip": "VID_20260211_220150_021.mp4",
      "in": 447,
      "out": 450,
      "speed": 1,
      "volume": 1,
      "subtitle": "두 손으로 몸판을 넓게 펼쳐 늘어난 길이/폭을 확인하는 동작, 클립 내 가장 뚜렷한 진행 변화"
    },
    {
      "clip": "VID_20260211_220150_021.mp4",
      "in": 452,
      "out": 512,
      "speed": 14,
      "volume": 1,
      "subtitle": "(빨리감기) 동일 앵글에서 뜨개질 반복 지속, 완성/전신/고양이 등장 없이 클립 끝(676초)까지 이어짐 - 배속 커넥터 후보"
    },
    {
      "clip": "VID_20260211_225303_022.mp4",
      "in": 3,
      "out": 6,
      "speed": 1,
      "volume": 1,
      "subtitle": "test"
    },
    {
      "clip": "VID_20260211_225420_023.mp4",
      "in": 644,
      "out": 647,
      "speed": 1,
      "volume": 1,
      "subtitle": "얽힌 검은 끈 더미 속에서 회색 니트 소매를 양손으로 들어올려 질감이 잠깐 드러남"
    },
    {
      "clip": "VID_20260212_001043_024.mp4",
      "in": 0,
      "out": 3,
      "speed": 1,
      "volume": 1,
      "subtitle": "그레이-블랙 스펙클 투톤 배색 뜨개 작업물이 나무 테이블 위에 놓여있고 원형바늘과 실이 걸려있음, 옆에 머그컵과 스마트폰 보임"
    },
    {
      "clip": "VID_20260212_223016_025.mp4",
      "in": 673,
      "out": 676,
      "speed": 1,
      "volume": 1,
      "subtitle": "체크무늬 바지를 입은 다른 사람의 팔이 프레임 앞쪽으로 들어와 잠든 고양이를 쓰다듬음. 얼굴 없이 팔과 고양이만 잡히는 안전한 손 클로즈업"
    },
    {
      "clip": "VID_20260213_001847_026.mp4",
      "in": 0.5,
      "out": 3.5,
      "speed": 1,
      "volume": 1,
      "subtitle": "나무 보드에 걸쳐진 회색+검정 스팽글 밑단 니트 조끼 전경, 아래쪽에 라벤더색 바지 입은 다리만 살짝 보임(얼굴 없음), 전체 클립 동안 거의 정지 상태"
    },
    {
      "clip": "VID_20260213_120922_027.mp4",
      "in": 28,
      "out": 31,
      "speed": 1,
      "volume": 1,
      "subtitle": "소매 낀 팔이 렌즈를 스치듯 가리는 근접샷, 도트 패턴 원단 질감 확대, 얼굴 미노출"
    },
    {
      "clip": "VID_20260213_123618_028.mp4",
      "in": 18,
      "out": 21,
      "speed": 1,
      "volume": 1,
      "subtitle": "테이블 위에 놓인 검은 바탕에 흰 비즈가 촘촘히 박힌 니트 원단, 옆으로 팔이 스쳐 지나가며 프레임 일부를 가림"
    },
    {
      "clip": "VID_20260213_221205_029.mp4",
      "in": 0,
      "out": 3,
      "speed": 1,
      "volume": 1,
      "subtitle": "나무 테이블 위 검은 뜨개 상의, 하단에 비즈/스팽글 장식, 원형바늘 걸쳐진 정적 오브젝트 샷"
    },
    {
      "clip": "VID_20260214_080622_030.mp4",
      "in": 180,
      "out": 183,
      "speed": 1,
      "volume": 1,
      "subtitle": "머리카락이 얼굴 대부분을 가린 상태로 검은 끈 뭉치를 양손으로 다루는 클로즈업, 손 동작만 선명하게 보이고 얼굴 노출 없음"
    },
    {
      "clip": "VID_20260214_080622_030.mp4",
      "in": 653,
      "out": 656,
      "speed": 1,
      "volume": 1,
      "subtitle": "머리카락이 얼굴을 완전히 덮은 채 검은 끈을 손끝으로 매듭짓는 디테일 손 클로즈업, 이 클립 전체에서 가장 깨끗하게 얼굴이 가려진 구간"
    },
    {
      "clip": "VID_20260214_083307_031.mp4",
      "in": 0,
      "out": 3,
      "speed": 1,
      "volume": 1,
      "subtitle": "완성된 검정 니트 조끼(밑단에 스팽글 장식, 목 부분에 코바늘 걸어둠)가 나무 바닥에 평평하게 펼쳐진 정적 오브젝트 샷, 옆에 대바늘/실뭉치/흰 상의 보임"
    },
    {
      "clip": "VID_20260214_083307_031.mp4",
      "in": 4,
      "out": 5,
      "speed": 1,
      "volume": 1,
      "subtitle": "흰 소매 손이 화면에 들어와 조끼 밑단 스팽글 부분을 살짝 만지는 손 클로즈업(3초 컷 필요시 실제로는 8초까지 동일 동작 이어짐, 5초 상한으로 컷)"
    },
    {
      "clip": "VID_20260214_083412_032.mp4",
      "in": 0,
      "out": 2,
      "speed": 1,
      "volume": 1,
      "subtitle": "바닥에 펼쳐진 회색/검정 스팽글 니트 조끼 전경, 손 없이 깔끔한 정적 오브젝트 샷"
    },
    {
      "clip": "VID_20260214_083412_032.mp4",
      "in": 3,
      "out": 6,
      "speed": 1,
      "volume": 1,
      "subtitle": "손이 들어와 니트 목둘레 부분을 손가락으로 잡고 만지는 클로즈업, 손목 위로는 안 보임"
    },
    {
      "clip": "VID_20260214_083412_032.mp4",
      "in": 7,
      "out": 10,
      "speed": 1,
      "volume": 1,
      "subtitle": "손이 빠지고 다시 니트 조끼 전경만 보이는 정적 샷, 시작 프레임과 거의 동일 구도"
    },
    {
      "clip": "VID_20260214_083437_033.mp4",
      "in": 0,
      "out": 3,
      "speed": 1,
      "volume": 1,
      "subtitle": "바닥에 널린 뜨개 재료(니트 조각, 실뭉치, 폰) 사이에서 손으로 검정 옷을 집어 살펴보는 도입 장면"
    },
    {
      "clip": "VID_20260214_083437_033.mp4",
      "in": 200,
      "out": 203,
      "speed": 1,
      "volume": 1,
      "subtitle": "정돈되어 있던 실이 갑자기 크게 헝클어진 뭉치로 변함, 빠르게 실을 풀어내는 손 모션 블러(프로깅 시작 순간)"
    },
    {
      "clip": "VID_20260214_083437_033.mp4",
      "in": 564,
      "out": 567.25,
      "speed": 1,
      "volume": 1,
      "subtitle": "프레임 상단 테이블 밑에서 흑백 고양이 머리가 처음 살짝 나타남"
    },
    {
      "clip": "VID_20260214_083437_033.mp4",
      "in": 945,
      "out": 948.25,
      "speed": 1,
      "volume": 1,
      "subtitle": "고양이 얼굴이 정면으로 또렷하게 보임, 귀 쫑긋 세우고 테이블 밑에서 이쪽을 살피는 모습"
    },
    {
      "clip": "VID_20260214_083437_033.mp4",
      "in": 1327,
      "out": 1330.25,
      "speed": 1,
      "volume": 1,
      "subtitle": "고양이가 테이블 밑에서 발만 보이며 걸어 물러나는 퇴장 순간"
    },
    {
      "clip": "VID_20260214_083437_033.mp4",
      "in": 1468,
      "out": 1471.25,
      "speed": 1,
      "volume": 1,
      "subtitle": "회색 스팽글 니트 조각과 검정 스팽글 니트 조각 두 개를 바닥에 나란히 펼쳐 비교하는 모습"
    },
    {
      "clip": "VID_20260214_091033_034.mp4",
      "in": 0,
      "out": 3.25,
      "speed": 1,
      "volume": 1,
      "subtitle": "나무 바닥 위 검정 스팽글 니트 원단과 회색/검정 실뭉치, 대바늘이 펼쳐진 정적 오브젝트 샷, 손이나 얼굴은 보이지 않음"
    },
    {
      "clip": "VID_20260214_120646_035.mp4",
      "in": 58,
      "out": 61.25,
      "speed": 1,
      "volume": 1,
      "subtitle": "소파 위에 놓인 회색 실뭉치(바늘 꽂힌 채)와 파우치, 연필. 정적 재료 샷"
    },
    {
      "clip": "VID_20260214_120646_035.mp4",
      "in": 356,
      "out": 359.25,
      "speed": 1,
      "volume": 1,
      "subtitle": "들어올린 회색+검정 스팽글 뜨개천에 얼굴이 거의 가려지고 뜨개바늘 쥔 두 손이 화면 중심"
    },
    {
      "clip": "VID_20260214_120646_035.mp4",
      "in": 632,
      "out": 635.25,
      "speed": 1,
      "volume": 1,
      "subtitle": "고양이가 화면 오른쪽 선반 옆 공간으로 걸어 들어와 전신이 보임(이동 중이라 약간 블러)"
    },
    {
      "clip": "VID_20260214_120646_035.mp4",
      "in": 693,
      "out": 696.25,
      "speed": 1,
      "volume": 1,
      "subtitle": "고양이가 나무 의자 다리 옆에 앉아 가만히 쉬고 있음, 배경에 정지된 채 또렷하게 보임"
    },
    {
      "clip": "VID_20260214_120646_035.mp4",
      "in": 1492,
      "out": 1495.25,
      "speed": 1,
      "volume": 1,
      "subtitle": "일어서서 짜던 옷을 몸통에 대보는 동작, 상반신 길이를 가늠하는 듯한 자세(얼굴은 프레임 위로 벗어나 안 보임)"
    },
    {
      "clip": "VID_20260214_133321_036.mp4",
      "in": 0,
      "out": 3,
      "speed": 1,
      "volume": 1,
      "subtitle": "회색 뜨개 조각과 검정+스팽글 밑단 뜨개 조각 두 개가 나무 바닥에 나란히 놓여 있음, 정지 상태"
    },
    {
      "clip": "VID_20260214_150555_040.mp4",
      "in": 4,
      "out": 6,
      "speed": 1,
      "volume": 1,
      "subtitle": "실외 재료 진열대에서 실내로 이동하며 단추 샘플 카드가 빼곡한 벽면이 드러남, 옆에 에어컨 실외기형 스탠드 유닛 보임"
    },
    {
      "clip": "VID_20260214_150555_040.mp4",
      "in": 6,
      "out": 9,
      "speed": 1,
      "volume": 1,
      "subtitle": "단추 샘플 카드 진열벽 클로즈업과 아래 서랍 속 색색의 비즈/단추가 칸칸이 정리된 모습"
    },
    {
      "clip": "VID_20260214_151729_041.mp4",
      "in": 0,
      "out": 3.25,
      "speed": 1,
      "volume": 1,
      "subtitle": "손이 흰 그릇을 들고 검정/브라운 별갑무늬/초록 단추들을 보여줌, 뒤로 야외 좌판 소품들과 눈 덮인 배경"
    },
    {
      "clip": "VID_20260214_152113_042.mp4",
      "in": 2,
      "out": 5,
      "speed": 1,
      "volume": 1,
      "subtitle": "파우치 두 개 전체가 선명하게 보임 - 하나는 회색 계열, 하나는 갈색/초록 계열 미키마우스 모양 완성물, 겉면에 로고 글씨(...Made) 보임, 야외 보도블럭 배경"
    },
    {
      "clip": "VID_20260214_175304_046.mp4",
      "in": 29,
      "out": 32,
      "speed": 1,
      "volume": 1,
      "subtitle": "바늘과 실이 교차하는 손동작 클로즈업, 실 한 가닥이 화면을 가로질러 다소 산만함"
    },
    {
      "clip": "VID_20260214_175304_046.mp4",
      "in": 74.5,
      "out": 77.5,
      "speed": 1,
      "volume": 1,
      "subtitle": "검은 레이스 뜨개 조각을 두 손으로 들고 스티치 짜는 중, 패턴 구멍 디테일이 선명하게 보임, 조명 밝고 프레임 안정적"
    },
    {
      "clip": "VID_20260214_175838_047.mp4",
      "in": 268,
      "out": 271.25,
      "speed": 1,
      "volume": 1,
      "subtitle": "들어 올린 뜨개 조각을 얼굴 앞에 바짝 대고 코바늘 뜨개 무늬를 살펴보는 클로즈업 — 편물과 손이 화면을 채우고 얼굴은 편물 뒤로 가려짐(이마만 살짝 보임, 입술 노출 없음)"
    },
    {
      "clip": "VID_20260214_175838_047.mp4",
      "in": 313,
      "out": 316.25,
      "speed": 1,
      "volume": 1,
      "subtitle": "바늘과 실을 쥔 손이 화면 가득한 클로즈업, 상단에 턱선만 살짝 보이고 입술은 보이지 않음 — 반대쪽 손이 프레임 오른쪽에서 들어오며 앵글이 하이앵글/오버헤드로 전환된 구간"
    },
    {
      "clip": "VID_20260214_183313_048.mp4",
      "in": 13,
      "out": 16.25,
      "speed": 1,
      "volume": 1,
      "subtitle": "검은 바탕에 흰 점무늬가 있는 뜨개천을 두 손으로 펼쳐 카메라 쪽으로 들어 보이는 장면, 얼굴은 천에 가려지고 모서리에 머리카락만 살짝 보임"
    },
    {
      "clip": "VID_20260214_183313_048.mp4",
      "in": 17,
      "out": 20,
      "speed": 1,
      "volume": 1,
      "subtitle": "팔과 손이 화면 전면을 가득 채우며 지나가는 클로즈업, 얼굴은 보이지 않고 배경에 줄무늬 옷과 선반 일부만 스침"
    },
    {
      "clip": "VID_20260215_005216_049.mp4",
      "in": 632,
      "out": 635.25,
      "speed": 1,
      "volume": 1,
      "subtitle": "뜨던 조각을 두 손으로 들어올려 펼쳐 보여줌 - 위쪽 회색 마블, 아래쪽 검정+흰 비즈 배색과 커프(단) 디테일이 드러남, 고개는 계속 숙인 채라 입술 안 보임"
    },
    {
      "clip": "VID_20260215_105630_050.mp4",
      "in": 0,
      "out": 3.25,
      "speed": 1,
      "volume": 1,
      "subtitle": "검정 니트 조끼(끝단에 스팽글/비즈 장식)가 옷걸이에 걸려 커튼 앞에 정지 상태로 보임, 완성물 정적 컷"
    },
    {
      "clip": "VID_20260215_112544_051.mp4",
      "in": 119,
      "out": 122.25,
      "speed": 1,
      "volume": 1,
      "subtitle": "빨간색 뜨개 도구(코바늘로 보임)를 쥐고 손을 움직이는 클로즈업, 니트 소재 위에서 작업 중"
    },
    {
      "clip": "VID_20260215_112544_051.mp4",
      "in": 160,
      "out": 163.25,
      "speed": 1,
      "volume": 1,
      "subtitle": "얼룩무늬 고양이가 화면 왼쪽 바닥을 가로질러 걸어가는 모습, 전신이 비교적 또렷하게 보임"
    },
    {
      "clip": "VID_20260215_114708_052.mp4",
      "in": 179,
      "out": 182,
      "speed": 1,
      "volume": 1,
      "subtitle": "무릎에 걸친 발에 신은 회색 니트 양말을 바늘로 뜨는 손 클로즈업"
    },
    {
      "clip": "VID_20260215_114708_052.mp4",
      "in": 659,
      "out": 662,
      "speed": 1,
      "volume": 1,
      "subtitle": "검은색 뜨개 아이템(모자로 추정)을 손에 쥐고 바늘로 뜨는 클로즈업"
    },
    {
      "clip": "VID_20260215_114708_052.mp4",
      "in": 777,
      "out": 780,
      "speed": 1,
      "volume": 1,
      "subtitle": "무릎 옆에 웅크린 검은 고양이 머리와 귀 윤곽이 얼핏 보이고 손이 그 쪽으로 움직임"
    },
    {
      "clip": "VID_20260215_124845_053.mp4",
      "in": 0,
      "out": 3.25,
      "speed": 1,
      "volume": 1,
      "subtitle": "나무 테이블 위 완성된 남색 니트 조끼 위에 Rare Made 브랜드 태그 두 개가 올려져 있음, 손이나 얼굴 없이 정적인 완성물+브랜드 태그 구도"
    },
    {
      "clip": "VID_20260215_124919_054.mp4",
      "in": 0,
      "out": 3,
      "speed": 1,
      "volume": 1,
      "subtitle": "테이블 위에 검정 니트 조끼와 소품(리모컨, 핑크색 케이스, 베이지 파우치, 폰)이 정리되어 있고 손이 폰을 들고 있는 도입 구도"
    },
    {
      "clip": "VID_20260215_124919_054.mp4",
      "in": 58,
      "out": 61.25,
      "speed": 1,
      "volume": 1,
      "subtitle": "양손으로 조끼 앞판에 단추를 실로 꿰매는 클로즈업"
    },
    {
      "clip": "VID_20260215_124919_054.mp4",
      "in": 88,
      "out": 91.25,
      "speed": 1,
      "volume": 1,
      "subtitle": "단추 여러 개가 조끼 앞판에 일렬로 놓여 있고 손이 위치를 정돈하는 모습"
    },
    {
      "clip": "VID_20260215_124919_054.mp4",
      "in": 134,
      "out": 137.25,
      "speed": 1,
      "volume": 1,
      "subtitle": "가위가 새로 등장했고 단추가 앞선 프레임보다 더 많이 달려 진행 상태가 바뀜"
    },
    {
      "clip": "VID_20260215_135135_055.mp4",
      "in": 0,
      "out": 3,
      "speed": 1,
      "volume": 1,
      "subtitle": "탁자 위에 펼쳐진 조끼 전체 모습(단추 여러 개, 밑단에 비즈 장식 라인) - 완성물을 보여주는 것으로 보이는 오버헤드 샷"
    },
    {
      "clip": "VID_20260215_135135_055.mp4",
      "in": 4,
      "out": 7,
      "speed": 1,
      "volume": 1,
      "subtitle": "단추와 목선 쪽으로 줌인한 클로즈업, 편물 텍스처와 단추 디테일이 선명하게 보임"
    },
    {
      "clip": "VID_20260215_135825_056.mp4",
      "in": 0,
      "out": 3,
      "speed": 1,
      "volume": 1,
      "subtitle": "회색 뜨개 완성물을 물에 담가 헹구는 장면, 정적인 오브젝트 클로즈업"
    },
    {
      "clip": "VID_20260215_140437_057.mp4",
      "in": 0,
      "out": 3,
      "speed": 1,
      "volume": 1,
      "subtitle": "완성된 검정 민소매 가디건(조끼)을 펼쳐서 보여주는 장면, 단추 여밈에 하단은 반짝이는 스팽글 장식 니트, 손이나 얼굴은 보이지 않음"
    },
    {
      "clip": "VID_20260215_142534_060.mp4",
      "in": 0,
      "out": 3,
      "speed": 1,
      "volume": 1,
      "subtitle": "완성된 짙은 남색 니트 조끼가 나무 테이블 위에 펼쳐져 있음, 가운데 회색 단추 플래킷과 하단 반짝이는 스팽글 트림이 보임, 전체가 프레임에 들어오는 와이드 샷"
    },
    {
      "clip": "VID_20260215_142534_060.mp4",
      "in": 9,
      "out": 12.25,
      "speed": 1,
      "volume": 1,
      "subtitle": "같은 조끼를 카메라가 서서히 줌인해 단추와 하단 스팽글 트림 질감이 더 가깝게 보이는 디테일 샷"
    },
    {
      "clip": "VID_20260216_081616_005_17_16.MP4",
      "in": 4,
      "out": 7.25,
      "speed": 1,
      "volume": 1,
      "subtitle": "뒤에서 본 니트 조끼 전신 착용샷, 팔을 자연스럽게 내리고 서 있음"
    },
    {
      "clip": "VID_20260216_081616_005_17_16.MP4",
      "in": 19,
      "out": 22.25,
      "speed": 1,
      "volume": 1,
      "subtitle": "뒤돌아선 채 팔을 양옆으로 펼쳐 조끼 핏을 보여주는 전신샷"
    },
    {
      "clip": "VID_20260216_081616_005_17_16.MP4",
      "in": 49,
      "out": 52.25,
      "speed": 1,
      "volume": 1,
      "subtitle": "앞에서 본 조끼 단추와 밑단 클로즈업, 손으로 옷단을 정리하는 중"
    }
  ],
  "bgm": [],
  "subtitleStyle": {
    "font": "Pretendard",
    "size": 36,
    "color": "#ffffff",
    "outlineColor": "#000000",
    "outlineWidth": 3,
    "position": "bottom",
    "margin": 40
  }
}